README
setup.py
tai64n/__init__.py
tai64n.egg-info/PKG-INFO
tai64n.egg-info/SOURCES.txt
tai64n.egg-info/dependency_links.txt
tai64n.egg-info/requires.txt
tai64n.egg-info/top_level.txt
