Metadata-Version: 1.0
Name: tai64n
Version: 0.3.3
Summary: Converts TAI64(n) string to datetime.datetime (UTC) object.
Home-page: http://bitbucket.org/hinnerk/py-tai64n/
Author: Hinnerk Haardt
Author-email: hinnerk@randnotizen.de
License: BSD
Platform: UNKNOWN
Classifier: Development Status :: 4 - Beta
Classifier: Intended Audience :: Developers
Classifier: License :: OSI Approved :: BSD License
Classifier: Operating System :: OS Independent
Classifier: Programming Language :: Python
Classifier: Topic :: Other/Nonlisted Topic
